sout/__init__.py
sout/test.py
sout-1.2.1.dist-info/METADATA
sout-1.2.1.dist-info/WHEEL
sout-1.2.1.dist-info/top_level.txt
sout-1.2.1.dist-info/RECORD
